{"appid": 1057850, "name": "Neon Boost", "developer": "Sample Text Studio", "publisher": "Sample Text Studio", "score_rank": "", "positive": 2239, "negative": 242, "userscore": 0, "owners": "200,000 .. 500,000", "average_forever": 0, "average_2weeks": 0, "median_forever": 0, "median_2weeks": 0, "price": "0", "initialprice": "0", "discount": "0", "ccu": 0, "languages": "English, Spanish - Spain, French, German, Portuguese - Brazil, Russian", "genre": "Action, Free To Play, Indie", "tags": {"Free to Play": 130, "Parkour": 88, "Action": 68, "First-Person": 64, "Indie": 58, "Platformer": 53, "FPS": 51, "Great Soundtrack": 45, "Runner": 43, "Difficult": 38, "1980s": 37, "Shooter": 35, "Atmospheric": 29, "Cyberpunk": 25, "Multiplayer": 18, "3D Platformer": 8}}