{"appid": 1579380, "name": "Shadow Tactics: Aiko's Choice", "developer": "Mimimi Games", "publisher": "Daedalic Entertainment", "score_rank": "", "positive": 4144, "negative": 292, "userscore": 0, "owners": "500,000 .. 1,000,000", "average_forever": 304, "average_2weeks": 242, "median_forever": 309, "median_2weeks": 242, "price": "499", "initialprice": "1999", "discount": "75", "ccu": 13, "languages": "English, German, Japanese, French, Italian, Spanish - Spain, Korean, Polish, Portuguese - Brazil, Russian, Simplified Chinese, Traditional Chinese, Turkish", "genre": "Indie, Strategy", "tags": {"Real Time Tactics": 161, "Strategy": 152, "Isometric": 133, "Stealth": 132, "Action": 127, "Adventure": 121, "RTS": 116, "Assassin": 109, "Puzzle": 102, "Atmospheric": 98, "Ninja": 96, "Historical": 94, "Tactical": 90, "Singleplayer": 88, "Survival": 82, "Indie": 62, "Violent": 60, "Difficult": 40, "Military": 34, "Building": 25}}