{"appid": 1643320, "name": "S.T.A.L.K.E.R. 2: Heart of Chornobyl", "developer": "GSC Game World", "publisher": "GSC Game World (worldwide), SEGA (Japan), 4Divinity (China and South East Asia)", "score_rank": "", "positive": 91274, "negative": 22072, "userscore": 0, "owners": "2,000,000 .. 5,000,000", "average_forever": 3018, "average_2weeks": 356, "median_forever": 1592, "median_2weeks": 234, "price": "4199", "initialprice": "5999", "discount": "30", "ccu": 2403, "languages": "English, French, Italian, German, Spanish - Spain, Japanese, Korean, Polish, Portuguese - Brazil, Russian, Simplified Chinese, Traditional Chinese, Ukrainian, Arabic, Czech, Spanish - Latin America, Turkish, Serbian", "genre": "Action, Adventure, RPG", "tags": {"Open World": 1312, "FPS": 1114, "Post-apocalyptic": 1070, "Survival": 1054, "Atmospheric": 978, "Singleplayer": 860, "Shooter": 839, "Exploration": 780, "RPG": 721, "Story Rich": 665, "First-Person": 643, "Action": 633, "Lore-Rich": 575, "Sci-fi": 552, "Nonlinear": 546, "Multiple Endings": 540, "Choices Matter": 495, "Immersive Sim": 482, "Realistic": 478, "Cinematic": 431}}