{"appid": 2248760, "name": "Car For Sale Simulator 2023", "developer": "Red Axe Games", "publisher": "Red Axe Games", "score_rank": "", "positive": 14778, "negative": 3674, "userscore": 0, "owners": "200,000 .. 500,000", "average_forever": 705, "average_2weeks": 69, "median_forever": 603, "median_2weeks": 69, "price": "1699", "initialprice": "1699", "discount": "0", "ccu": 220, "languages": "English, Turkish, French, Italian, German, Spanish - Spain, Japanese, Russian, Arabic, Portuguese - Brazil, Danish, Dutch, Finnish, Traditional Chinese, Polish, Hungarian, Norwegian, Portuguese - Portugal, Ukrainian, Greek, Czech, Swedish", "genre": "Indie, Simulation", "tags": {"Driving": 288, "Trading": 268, "Immersive Sim": 265, "Automobile Sim": 255, "Simulation": 253, "FPS": 247, "Multiplayer": 239, "Life Sim": 218, "3D": 204, "Open World": 204, "First-Person": 201, "Realistic": 166, "Conversation": 166, "Family Friendly": 140, "Cinematic": 117, "Singleplayer": 105, "America": 104, "Modern": 87, "Inventory Management": 76, "Early Access": 59}}