{"appid": 594330, "name": "Visage", "developer": "SadSquare Studio", "publisher": "SadSquare Studio", "score_rank": "", "positive": 8368, "negative": 1453, "userscore": 0, "owners": "200,000 .. 500,000", "average_forever": 266, "average_2weeks": 0, "median_forever": 195, "median_2weeks": 0, "price": "3499", "initialprice": "3499", "discount": "0", "ccu": 24, "languages": "English, French, Italian, Spanish - Spain, Arabic, Bulgarian, Dutch, Greek, Portuguese - Portugal, Portuguese - Brazil, Russian, Spanish - Latin America, Swedish, Ukrainian, German, Japanese, Korean, Simplified Chinese, Turkish, Hungarian, Polish", "genre": "Action, Adventure, Indie, Simulation", "tags": {"Horror": 402, "Psychological Horror": 303, "Survival Horror": 185, "Dark": 163, "Multiplayer": 154, "First-Person": 153, "Singleplayer": 132, "Atmospheric": 120, "Adventure": 106, "Indie": 90, "Violent": 84, "Exploration": 82, "Walking Simulator": 80, "Realistic": 79, "Surreal": 68, "Story Rich": 61, "Simulation": 50, "Early Access": 42, "Action": 37, "Experimental": 37}}